fastpf/__init__.py
fastpf/log.py
fastpf/powerflow.py
fastpf/powerflow_methods.py
fastpf/process_grid.py
fastpf/validation.py
fastpf/grid_reduction/__init__.py
fastpf/grid_reduction/lossless.py
fastpf/grid_reduction/lossy.py
fastpf/plotting/__init__.py
fastpf/plotting/diss.mplstyle
fastpf/plotting/plot_voltage.py
fastpf/plotting/plotting.py
fastpf-0.0.8.dist-info/LICENSE
fastpf-0.0.8.dist-info/WHEEL
fastpf-0.0.8.dist-info/METADATA
fastpf-0.0.8.dist-info/RECORD
